ttrun/__init__.py
ttrun/cmd.py
ttrun/tests/__init__.py
ttrun/tests/test_ttrun.py
ttrun-1.0.5.dist-info/DESCRIPTION.rst
ttrun-1.0.5.dist-info/METADATA
ttrun-1.0.5.dist-info/RECORD
ttrun-1.0.5.dist-info/WHEEL
ttrun-1.0.5.dist-info/entry_points.txt
ttrun-1.0.5.dist-info/metadata.json
ttrun-1.0.5.dist-info/pbr.json
ttrun-1.0.5.dist-info/top_level.txt
