Metadata-Version: 2.0
Name: ttrun
Version: 1.0.5
Summary: Simple CLI to run testtools tests
Home-page: http://git.inaugust.com/cgit/ttrun/
Author: Monty Taylor
Author-email: mordred@inaugust.com
License: UNKNOWN
Platform: UNKNOWN
Classifier: Intended Audience :: Developers
Classifier: License :: OSI Approved :: GNU General Public License v3 or later (GPLv3+)
Classifier: Operating System :: POSIX :: Linux
Classifier: Programming Language :: Python
Classifier: Programming Language :: Python :: 2
Classifier: Programming Language :: Python :: 2.7
Classifier: Programming Language :: Python :: 3
Classifier: Programming Language :: Python :: 3.4
Classifier: Programming Language :: Python :: 3.5
Requires-Dist: pbr (>=1.6)
Requires-Dist: testtools
